db2/__init__.py
db2/__main__.py
db2/backend.py
db2/orm.py
db2/session.py
db2-0.1.0.dist-info/METADATA
db2-0.1.0.dist-info/RECORD
db2-0.1.0.dist-info/WHEEL
db2-0.1.0.dist-info/top_level.txt
tests/__init__.py
tests/models.py
tests/settings.py
tests/tests.py
